arcticspas/__init__.py
arcticspas/client.py
arcticspas/errors.py
arcticspas/py.typed
arcticspas/types.py
arcticspas/api/__init__.py
arcticspas/api/spa_control/__init__.py
arcticspas/api/spa_control/v2_blower.py
arcticspas/api/spa_control/v2_boost.py
arcticspas/api/spa_control/v2_easy_mode.py
arcticspas/api/spa_control/v2_filter.py
arcticspas/api/spa_control/v2_fogger.py
arcticspas/api/spa_control/v2_light.py
arcticspas/api/spa_control/v2_pump.py
arcticspas/api/spa_control/v2_spa.py
arcticspas/api/spa_control/v2_temperature.py
arcticspas/api/spa_control/v2sds.py
arcticspas/api/spa_control/v2yess.py
arcticspas/models/__init__.py
arcticspas/models/v2_blower_blower.py
arcticspas/models/v2_blower_json_body.py
arcticspas/models/v2_blower_json_body_state.py
arcticspas/models/v2_easy_mode_json_body.py
arcticspas/models/v2_easy_mode_json_body_state.py
arcticspas/models/v2_filter_json_body.py
arcticspas/models/v2_filter_json_body_state.py
arcticspas/models/v2_fogger_json_body.py
arcticspas/models/v2_fogger_json_body_state.py
arcticspas/models/v2_light_json_body.py
arcticspas/models/v2_light_json_body_state.py
arcticspas/models/v2_pump_json_body.py
arcticspas/models/v2_pump_json_body_state.py
arcticspas/models/v2_pump_pump.py
arcticspas/models/v2_spa_response_200.py
arcticspas/models/v2_temperature_json_body.py
arcticspas/models/v2sds_json_body.py
arcticspas/models/v2sds_json_body_state.py
arcticspas/models/v2yess_json_body.py
arcticspas/models/v2yess_json_body_state.py
tests/__init__.py
tests/test_basics.py
arcticspas-2.0.dist-info/LICENSE
arcticspas-2.0.dist-info/METADATA
arcticspas-2.0.dist-info/WHEEL
arcticspas-2.0.dist-info/top_level.txt
arcticspas-2.0.dist-info/RECORD
