Metadata-Version: 2.1
Name: arcticspas
Version: 2.0
Summary: A client library for accessing Arctic Spas API
Requires-Python: >=3.8, <4
License-File: LICENSE
Requires-Dist: httpx <0.26.0,>=0.20.0
Requires-Dist: attrs >=21.3.0
Requires-Dist: python-dateutil <3,>=2.8.0
